{
  "name": "root",
  "desc": "",
  "file": "rootNode",
  "type": null,
  "posX": 250.0,
  "posY": 120.0,
  "index": 0,
  "fold": false,
  "data": {
    "restart": "1"
  },
  "children": [
    {
      "name": "selector",
      "desc": "",
      "file": "selectorNode",
      "type": "composites/selectorNode",
      "posX": 250.0,
      "posY": 240.0,
      "index": 1,
      "fold": false,
      "data": {
        "abort": "None"
      },
      "children": [
        {
          "name": "parallel",
          "desc": "",
          "file": "parallelNode",
          "type": "composites/parallelNode",
          "posX": 200.0,
          "posY": 360.0,
          "index": 2,
          "fold": false,
          "data": {
            "abort": "None"
          },
          "children": [
            {
              "name": "日志",
              "desc": "",
              "file": "logNode",
              "type": "actions/common/logNode",
              "posX": 200.0,
              "posY": 480.0,
              "index": 3,
              "fold": false,
              "data": {
                "msg": "111"
              },
              "children": null
            }
          ]
        },
        {
          "name": "parallel",
          "desc": "",
          "file": "parallelNode",
          "type": "composites/parallelNode",
          "posX": 300.0,
          "posY": 360.0,
          "index": 4,
          "fold": false,
          "data": {
            "abort": "None"
          },
          "children": [
            {
              "name": "日志",
              "desc": "",
              "file": "logNode",
              "type": "actions/common/logNode",
              "posX": 300.0,
              "posY": 480.0,
              "index": 5,
              "fold": false,
              "data": {
                "msg": "222"
              },
              "children": null
            }
          ]
        }
      ]
    }
  ]
}